{
  "implemented": true,
  "nationalPokedexNumber": 429,
  "name": "Mismagius",
  "primaryType": "ghost",
  "maleRatio": 0.5,
  "height": 9,
  "weight": 44,
  "pokedex": [
    "cobblemon.species.mismagius.desc"
  ],
  "labels": [
    "gen4"
  ],
  "aspects": [],
  "abilities": [
    "levitate",
    "h:levitate"
  ],
  "eggGroups": [
    "amorphous"
  ],
  "baseStats": {
    "hp": 60,
    "attack": 60,
    "defence": 60,
    "special_attack": 105,
    "special_defence": 105,
    "speed": 105
  },
  "evYield": {
    "hp": 0,
    "attack": 0,
    "defence": 0,
    "special_attack": 1,
    "special_defence": 1,
    "speed": 0
  },
  "baseExperienceYield": 173,
  "experienceGroup": "fast",
  "catchRate": 45,
  "eggCycles": 25,
  "baseFriendship": 35,
  "baseScale": 0.8,
  "hitbox": {
    "width": 1,
    "height": 2.2,
    "fixed": false
  },
  "drops": {
    "amount": 3,
    "entries": [
      {
        "item": "minecraft:phantom_membrane",
        "percentage": 5.0
      },
      {
        "item": "cobblemon:spell_tag",
        "percentage": 5.0
      },
      {
        "item": "cobblemon:kasib_berry",
        "percentage": 5.0
      }
    ]
  },
  "moves": [
    "1:luckychant",
    "1:magicalleaf",
    "1:growl",
    "1:psywave",
    "1:spite",
    "1:astonish",
    "1:mysticalfire",
    "1:powergem",
    "1:phantomforce",
    "1:meanlook",
    "1:perishsong",
    "1:confusion",
    "egg:curse",
    "egg:destinybond",
    "egg:imprison",
    "egg:mefirst",
    "egg:memento",
    "egg:screech",
    "egg:shadowsneak",
    "egg:spite",
    "egg:suckerpunch",
    "egg:wonderroom",
    "tm:allyswitch",
    "tm:burningjealousy",
    "tm:calmmind",
    "tm:chargebeam",
    "tm:charm",
    "tm:confuseray",
    "tm:curse",
    "tm:darkpulse",
    "tm:dazzlinggleam",
    "tm:drainingkiss",
    "tm:dreameater",
    "tm:echoedvoice",
    "tm:embargo",
    "tm:endure",
    "tm:energyball",
    "tm:facade",
    "tm:faketears",
    "tm:flash",
    "tm:foulplay",
    "tm:futuresight",
    "tm:gigaimpact",
    "tm:grassknot",
    "tm:grudge",
    "tm:headbutt",
    "tm:healbell",
    "tm:helpinghand",
    "tm:hex",
    "tm:hyperbeam",
    "tm:hypervoice",
    "tm:icywind",
    "tm:imprison",
    "tm:laserfocus",
    "tm:lashout",
    "tm:magicalleaf",
    "tm:magiccoat",
    "tm:magicroom",
    "tm:mysticalfire",
    "tm:nastyplot",
    "tm:nightshade",
    "tm:ominouswind",
    "tm:painsplit",
    "tm:payback",
    "tm:phantomforce",
    "tm:poltergeist",
    "tm:powergem",
    "tm:protect",
    "tm:psybeam",
    "tm:psychic",
    "tm:psychicnoise",
    "tm:psychup",
    "tm:psyshock",
    "tm:raindance",
    "tm:rest",
    "tm:scaryface",
    "tm:screech",
    "tm:shadowball",
    "tm:shockwave",
    "tm:skillswap",
    "tm:sleeptalk",
    "tm:snatch",
    "tm:snowscape",
    "tm:spite",
    "tm:storedpower",
    "tm:substitute",
    "tm:suckerpunch",
    "tm:sunnyday",
    "tm:swift",
    "tm:taunt",
    "tm:telekinesis",
    "tm:terablast",
    "tm:thief",
    "tm:thunder",
    "tm:thunderbolt",
    "tm:thunderwave",
    "tm:torment",
    "tm:trick",
    "tm:trickroom",
    "tm:willowisp",
    "tm:wonderroom",
    "tutor:allyswitch",
    "tutor:burningjealousy",
    "tutor:calmmind",
    "tutor:chargebeam",
    "tutor:darkpulse",
    "tutor:dazzlinggleam",
    "tutor:energyball",
    "tutor:foulplay",
    "tutor:gigaimpact",
    "tutor:healbell",
    "tutor:helpinghand",
    "tutor:hyperbeam",
    "tutor:hypervoice",
    "tutor:icywind",
    "tutor:laserfocus",
    "tutor:lashout",
    "tutor:magicalleaf",
    "tutor:magiccoat",
    "tutor:magicroom",
    "tutor:mysticalfire",
    "tutor:ominouswind",
    "tutor:painsplit",
    "tutor:poltergeist",
    "tutor:psychic",
    "tutor:rest",
    "tutor:shadowball",
    "tutor:shockwave",
    "tutor:skillswap",
    "tutor:sleeptalk",
    "tutor:snatch",
    "tutor:spite",
    "tutor:suckerpunch",
    "tutor:swift",
    "tutor:telekinesis",
    "tutor:thunderbolt",
    "tutor:trick",
    "tutor:wonderroom"
  ],
  "preEvolution": "misdreavus",
  "evolutions": []
}