{
  "implemented": true,
  "nationalPokedexNumber": 20,
  "name": "Raticate",
  "primaryType": "normal",
  "maleRatio": 0.5,
  "height": 7,
  "weight": 185,
  "pokedex": [
    "cobblemon.species.raticate.desc"
  ],
  "labels": [
    "gen1",
    "kantonian_form"
  ],
  "aspects": [],
  "abilities": [
    "runaway",
    "guts",
    "h:hustle"
  ],
  "eggGroups": [
    "field"
  ],
  "baseStats": {
    "hp": 55,
    "attack": 81,
    "defence": 60,
    "special_attack": 50,
    "special_defence": 70,
    "speed": 97
  },
  "evYield": {
    "hp": 0,
    "attack": 0,
    "defence": 0,
    "special_attack": 0,
    "special_defence": 0,
    "speed": 2
  },
  "baseExperienceYield": 145,
  "experienceGroup": "medium_fast",
  "catchRate": 127,
  "eggCycles": 15,
  "baseFriendship": 50,
  "features": [
    "alolan"
  ],
  "baseScale": 0.8,
  "hitbox": {
    "width": 0.7,
    "height": 1.1,
    "fixed": false
  },
  "behaviour": {
    "moving": {
      "walk": {
        "walkSpeed": 0.33
      }
    },
    "resting": {
      "canSleep": true,
      "light": "0-4"
    }
  },
  "drops": {
    "amount": 3,
    "entries": [
      {
        "item": "minecraft:rotten_flesh",
        "quantityRange": "0-2"
      },
      {
        "item": "cobblemon:chilan_berry",
        "percentage": 5.0
      }
    ]
  },
  "moves": [
    "1:swordsdance",
    "1:tackle",
    "1:tailwhip",
    "1:quickattack",
    "1:focusenergy",
    "1:scaryface",
    "10:bite",
    "13:pursuit",
    "16:hyperfang",
    "19:assurance",
    "24:crunch",
    "29:suckerpunch",
    "34:superfang",
    "39:doubleedge",
    "44:endeavor",
    "egg:bite",
    "egg:counter",
    "egg:finalgambit",
    "egg:flamewheel",
    "egg:furyswipes",
    "egg:mefirst",
    "egg:swagger",
    "tm:assurance",
    "tm:beatup",
    "tm:blizzard",
    "tm:bodyslam",
    "tm:chargebeam",
    "tm:closecombat",
    "tm:covet",
    "tm:crunch",
    "tm:cut",
    "tm:dig",
    "tm:doubleedge",
    "tm:endeavor",
    "tm:endure",
    "tm:facade",
    "tm:focusenergy",
    "tm:gigaimpact",
    "tm:grassknot",
    "tm:headbutt",
    "tm:hyperbeam",
    "tm:icebeam",
    "tm:icywind",
    "tm:irontail",
    "tm:laserfocus",
    "tm:lastresort",
    "tm:mudslap",
    "tm:pluck",
    "tm:protect",
    "tm:psychicfangs",
    "tm:raindance",
    "tm:rest",
    "tm:retaliate",
    "tm:revenge",
    "tm:reversal",
    "tm:roar",
    "tm:rocksmash",
    "tm:scaryface",
    "tm:screech",
    "tm:shadowball",
    "tm:shockwave",
    "tm:sleeptalk",
    "tm:sludgebomb",
    "tm:stompingtantrum",
    "tm:strength",
    "tm:substitute",
    "tm:suckerpunch",
    "tm:sunnyday",
    "tm:superfang",
    "tm:swagger",
    "tm:swordsdance",
    "tm:takedown",
    "tm:taunt",
    "tm:terablast",
    "tm:thief",
    "tm:throatchop",
    "tm:thunder",
    "tm:thunderbolt",
    "tm:thunderwave",
    "tm:uproar",
    "tm:wildcharge",
    "tm:workup",
    "tm:zenheadbutt",
    "tutor:chargebeam",
    "tutor:covet",
    "tutor:endeavor",
    "tutor:focusenergy",
    "tutor:gigaimpact",
    "tutor:hyperbeam",
    "tutor:icebeam",
    "tutor:icywind",
    "tutor:irontail",
    "tutor:laserfocus",
    "tutor:lastresort",
    "tutor:mudslap",
    "tutor:psychic",
    "tutor:rest",
    "tutor:rocksmash",
    "tutor:shadowball",
    "tutor:shockwave",
    "tutor:sleeptalk",
    "tutor:sludgebomb",
    "tutor:stompingtantrum",
    "tutor:suckerpunch",
    "tutor:superfang",
    "tutor:throatchop",
    "tutor:thunderbolt",
    "tutor:uproar",
    "tutor:wildcharge",
    "tutor:zenheadbutt"
  ],
  "preEvolution": "rattata",
  "evolutions": [],
  "forms": [
    {
      "name": "Alola",
      "primaryType": "dark",
      "secondaryType": "normal",
      "maleRatio": 0.5,
      "height": 7,
      "weight": 255,
      "pokedex": [
        "cobblemon.species.raticate-alola.desc"
      ],
      "labels": [
        "gen7",
        "alolan_form"
      ],
      "aspects": [
        "alolan"
      ],
      "abilities": [
        "gluttony",
        "hustle",
        "h:thickfat"
      ],
      "baseStats": {
        "hp": 75,
        "attack": 71,
        "defence": 70,
        "special_attack": 40,
        "special_defence": 80,
        "speed": 77
      },
      "drops": {
        "amount": 3,
        "entries": [
          {
            "item": "minecraft:rotten_flesh",
            "quantityRange": "0-2"
          },
          {
            "item": "cobblemon:pecha_berry",
            "percentage": 5.0
          }
        ]
      },
      "moves": [
        "1:scaryface",
        "1:swordsdance",
        "1:tackle",
        "1:tailwhip",
        "1:quickattack",
        "1:focusenergy",
        "10:bite",
        "13:pursuit",
        "16:hyperfang",
        "19:assurance",
        "24:crunch",
        "29:suckerpunch",
        "34:superfang",
        "39:doubleedge",
        "44:endeavor",
        "egg:counter",
        "egg:finalgambit",
        "egg:furyswipes",
        "egg:mefirst",
        "egg:revenge",
        "egg:reversal",
        "egg:snatch",
        "egg:stockpile",
        "egg:swallow",
        "egg:switcheroo",
        "egg:uproar",
        "tm:assurance",
        "tm:beatup",
        "tm:blizzard",
        "tm:bodyslam",
        "tm:bulkup",
        "tm:burningjealousy",
        "tm:closecombat",
        "tm:covet",
        "tm:crunch",
        "tm:darkpulse",
        "tm:dig",
        "tm:doubleedge",
        "tm:embargo",
        "tm:endeavor",
        "tm:endure",
        "tm:facade",
        "tm:focusenergy",
        "tm:gigaimpact",
        "tm:grassknot",
        "tm:hyperbeam",
        "tm:icebeam",
        "tm:icywind",
        "tm:irontail",
        "tm:knockoff",
        "tm:lashout",
        "tm:lastresort",
        "tm:protect",
        "tm:psychicfangs",
        "tm:quash",
        "tm:raindance",
        "tm:rest",
        "tm:retaliate",
        "tm:revenge",
        "tm:reversal",
        "tm:roar",
        "tm:scaryface",
        "tm:screech",
        "tm:shadowball",
        "tm:shockwave",
        "tm:sleeptalk",
        "tm:sludgebomb",
        "tm:sludgewave",
        "tm:snarl",
        "tm:snatch",
        "tm:stompingtantrum",
        "tm:substitute",
        "tm:suckerpunch",
        "tm:sunnyday",
        "tm:superfang",
        "tm:swordsdance",
        "tm:taunt",
        "tm:terablast",
        "tm:thief",
        "tm:throatchop",
        "tm:thunder",
        "tm:thunderbolt",
        "tm:thunderwave",
        "tm:torment",
        "tm:uproar",
        "tm:venoshock",
        "tm:zenheadbutt",
        "tutor:bulkup",
        "tutor:burningjealousy",
        "tutor:covet",
        "tutor:darkpulse",
        "tutor:endeavor",
        "tutor:focusenergy",
        "tutor:gigaimpact",
        "tutor:hyperbeam",
        "tutor:icebeam",
        "tutor:icywind",
        "tutor:irontail",
        "tutor:knockoff",
        "tutor:lashout",
        "tutor:lastresort",
        "tutor:psychic",
        "tutor:rest",
        "tutor:shadowball",
        "tutor:shockwave",
        "tutor:sleeptalk",
        "tutor:sludgebomb",
        "tutor:snarl",
        "tutor:snatch",
        "tutor:stompingtantrum",
        "tutor:suckerpunch",
        "tutor:superfang",
        "tutor:throatchop",
        "tutor:thunderbolt",
        "tutor:uproar",
        "tutor:zenheadbutt"
      ],
      "preEvolution": "rattata alolan",
      "evolutions": [],
      "battleOnly": false
    }
  ]
}